cliasi/__about__.py
cliasi/__init__.py
cliasi/cliasi.py
cliasi/constants.py
cliasi/logging_handler.py
cliasi/py.typed
cliasi-0.4.2.dist-info/licenses/LICENSE
cliasi-0.4.2.dist-info/METADATA
cliasi-0.4.2.dist-info/WHEEL
cliasi-0.4.2.dist-info/top_level.txt
cliasi-0.4.2.dist-info/RECORD
