Metadata-Version: 2.4
Name: cliasi
Version: 0.4.2
Summary: Have a nice looking, simple cli in seconds
Author-email: Qrashi <fritz@vibe.ac>
License-Expression: GPL-3.0-or-later
Project-URL: Homepage, https://github.com/IgnyteX-Labs/cliasi
Project-URL: Issues, https://github.com/IgnyteX-Labs/cliasi/issues
Project-URL: Documentation, https://cliasi.readthedocs.io/
Classifier: Programming Language :: Python :: 3
Classifier: Operating System :: OS Independent
Requires-Python: >=3.10
License-File: LICENSE
Dynamic: license-file
